MathematicianHelper/__init__.py
MathematicianHelper/algebra.py
MathematicianHelper/arithmetic.py
MathematicianHelper/calculus.py
MathematicianHelper/numerical.py
MathematicianHelper-0.1.0.dist-info/LICENSE
MathematicianHelper-0.1.0.dist-info/METADATA
MathematicianHelper-0.1.0.dist-info/WHEEL
MathematicianHelper-0.1.0.dist-info/top_level.txt
MathematicianHelper-0.1.0.dist-info/RECORD
