Metadata-Version: 2.2
Name: MathematicianHelper
Version: 0.1.0
Summary: A Python package for solving mathematical problems.
Home-page: https://github.com/lakshay-goyal/MathematicianHelper
Author: Lakshay
Author-email: lakshaygoyal201@gmail.com
Classifier: Programming Language :: Python :: 3
Classifier: License :: OSI Approved :: MIT License
Classifier: Operating System :: OS Independent
Requires-Python: >=3.6
License-File: LICENSE
Requires-Dist: numpy
Requires-Dist: sympy
Dynamic: author
Dynamic: author-email
Dynamic: classifier
Dynamic: description
Dynamic: description-content-type
Dynamic: home-page
Dynamic: requires-dist
Dynamic: requires-python
Dynamic: summary
